typing_arguments/__init__.py
typing_arguments/generic_arguments.py
typing_arguments/py.typed
typing_arguments-0.2.1.dist-info/licenses/LICENSE
typing_arguments-0.2.1.dist-info/WHEEL
typing_arguments-0.2.1.dist-info/METADATA
typing_arguments-0.2.1.dist-info/RECORD
