Metadata-Version: 2.4
Name: typing-arguments
Version: 0.2.1
Summary: Store references of your typing arguments to be available at runtime.
Author: TEAM23 GmbH
Author-email: TEAM23 GmbH <info@team23.de>
License-Expression: MIT
License-File: LICENSE
Requires-Dist: pydantic>=2.0.0,<3.0.0 ; extra == 'pydantic'
Requires-Python: >=3.10
Project-URL: Repository, https://github.com/team23/typing-arguments
Provides-Extra: pydantic
